TRITON_SWMM_toolkit/TRITON_SWMM_toolkit.py
TRITON_SWMM_toolkit/__init__.py
TRITON_SWMM_toolkit/__main__.py
TRITON_SWMM_toolkit/cli.py
TRITON_SWMM_toolkit/utils.py
triton_swmm_toolkit-0.1.0.dist-info/licenses/LICENSE
triton_swmm_toolkit-0.1.0.dist-info/METADATA
triton_swmm_toolkit-0.1.0.dist-info/WHEEL
triton_swmm_toolkit-0.1.0.dist-info/entry_points.txt
triton_swmm_toolkit-0.1.0.dist-info/top_level.txt
triton_swmm_toolkit-0.1.0.dist-info/RECORD
