Metadata-Version: 2.4
Name: TRITON-SWMM_toolkit
Version: 0.1.0
Summary: Tools for running and processing TRITON-SWMM models.
Author-email: Daniel Lassiter <daniel.lassiter@outlook.com>
Maintainer-email: Daniel Lassiter <daniel.lassiter@outlook.com>
License: MIT
Project-URL: bugs, https://github.com/lassiterdc/TRITON_SWMM_toolkit/issues
Project-URL: changelog, https://github.com/lassiterdc/TRITON_SWMM_toolkit/blob/master/changelog.md
Project-URL: homepage, https://github.com/lassiterdc/TRITON_SWMM_toolkit
Requires-Python: >=3.10
License-File: LICENSE
Requires-Dist: typer
Provides-Extra: test
Requires-Dist: coverage; extra == "test"
Requires-Dist: pytest; extra == "test"
Requires-Dist: ruff; extra == "test"
Requires-Dist: ty; extra == "test"
Requires-Dist: ipdb; extra == "test"
Dynamic: license-file
